ocrtestdata/__init__.py
ocrtestdata/cli.py
ocrtestdata/generator.py
ocrtestdata/io_utils.py
ocrtestdata/fonts/CONTRIBUTING.txt
ocrtestdata/fonts/FONTLOG.txt
ocrtestdata/fonts/LICENCE-FAQ.txt
ocrtestdata/fonts/LICENCE.txt
ocrtestdata/fonts/README.txt
ocrtestdata/fonts/TRADEMARKS.txt
ocrtestdata/fonts/Ubuntu-B.ttf
ocrtestdata/fonts/Ubuntu-R.ttf
ocrtestdata/fonts/copyright.txt
ocrtestdata-0.1.0.dist-info/licenses/LICENSE
ocrtestdata-0.1.0.dist-info/METADATA
ocrtestdata-0.1.0.dist-info/WHEEL
ocrtestdata-0.1.0.dist-info/entry_points.txt
ocrtestdata-0.1.0.dist-info/top_level.txt
ocrtestdata-0.1.0.dist-info/RECORD
