Metadata-Version: 2.4
Name: ocrtestdata
Version: 0.1.0
Summary: Generate large amounts of image-based PDF test data for file-based OCR and Document Management Solutions.
Author-email: Björn Seipel <support@digidigital.de>
License: MIT
Project-URL: Homepage, https://digidigital.de
Project-URL: Repository, https://github.com/digidigital/ocrtestdata
Project-URL: Support, https://github.com/digidigital/ocrtestdata/issues
Keywords: ocr,pdf,testing,tests,automation
Classifier: Development Status :: 4 - Beta
Classifier: Intended Audience :: Developers
Classifier: Intended Audience :: System Administrators
Classifier: Programming Language :: Python :: 3.9
Classifier: Programming Language :: Python :: 3.10
Classifier: Programming Language :: Python :: 3.11
Classifier: Programming Language :: Python :: 3.12
Classifier: Operating System :: OS Independent
Requires-Python: >=3.9
License-File: LICENSE
Requires-Dist: Faker>=18.0.0
Requires-Dist: Pillow>=9.0.0
Requires-Dist: qrcode[pil]>=7.0
Dynamic: license-file
